[
  {
    "source": "manuell",
    "complete": true,
    "client": "kkpok",
    "title": "Führungsfeedback",
    "amount": 120000,
    "list": [
      {
        "name": "Sara Kaufmann",
        "pct": 50,
        "money": 60000
      },
      {
        "name": "Christopher van den Hövel",
        "pct": 35,
        "money": 42000
      },
      {
        "name": "Merlin Klein",
        "pct": 15,
        "money": 18000
      }
    ],
    "totals": {
      "cs": 100,
      "konzept": 100,
      "pitch": 0
    },
    "weights": [
      {
        "key": "cs",
        "weight": 50
      },
      {
        "key": "konzept",
        "weight": 50
      },
      {
        "key": "pitch",
        "weight": 0
      }
    ],
    "submittedBy": "Abdi Tekin",
    "ts": 1759934451629,
    "id": "e43d2de4-4a58-4a07-8106-0319612f1218",
    "projectNumber": ""
  },
  {
    "id": "f9df1710-8f6a-4326-b378-57894c9b3956",
    "ts": 1759922050555,
    "source": "hubspot",
    "complete": true,
    "title": "Change-Begleitung",
    "client": "DRV Bund",
    "amount": 250000,
    "hubspotId": "45326972175",
    "pipeline": "default",
    "dealstage": "closedwon",
    "closedate": null,
    "modified": null,
    "list": [
      {
        "name": "Christopher van den Hövel",
        "pct": 100,
        "money": 250000
      }
    ],
    "totals": {
      "cs": 100,
      "konzept": 0,
      "pitch": 0
    },
    "weights": [
      {
        "key": "cs",
        "weight": 100
      },
      {
        "key": "konzept",
        "weight": 0
      },
      {
        "key": "pitch",
        "weight": 0
      }
    ],
    "submittedBy": "Abdi Tekin"
  },
  {
    "source": "manuell",
    "complete": true,
    "client": "klmlk",
    "title": "lkmlkm",
    "amount": 50000,
    "list": [
      {
        "name": "Sophie But",
        "pct": 81,
        "money": 40500
      },
      {
        "name": "Dilâra Dayakli",
        "pct": 19,
        "money": 9500
      }
    ],
    "totals": {
      "cs": 100,
      "konzept": 100,
      "pitch": 0
    },
    "weights": [
      {
        "key": "cs",
        "weight": 62
      },
      {
        "key": "konzept",
        "weight": 38
      },
      {
        "key": "pitch",
        "weight": 0
      }
    ],
    "submittedBy": "Abdi Tekin",
    "projectNumber": "",
    "ts": 1759934548143,
    "id": "1ff8dac5-6699-47ec-a654-a735c56c3d16"
  }
]